requirements_compare/__init__.py
requirements_compare/main.py
requirements_compare/py.typed
requirements_compare-0.2.0.dist-info/METADATA
requirements_compare-0.2.0.dist-info/WHEEL
requirements_compare-0.2.0.dist-info/entry_points.txt
requirements_compare-0.2.0.dist-info/licenses/AUTHORS.rst
requirements_compare-0.2.0.dist-info/licenses/LICENCE
requirements_compare-0.2.0.dist-info/RECORD
