Metadata-Version: 2.1
Name: requirements_compare
Version: 0.2.0
Summary: A CLI that generate a version changelog based on git history and local requirement file.
Project-URL: Homepage, https://lab.frogg.it/swepy/OSOC/requirement-compare
Project-URL: Bug Tracker, https://lab.frogg.it/swepy/OSOC/requirement-compare
Author-email: Dorian Turba <contact.r9qrp@8shield.net>, Simon Desnoyers <0d3s3n@gmail.com>
License-File: AUTHORS.rst
License-File: LICENCE
Classifier: Development Status :: 3 - Alpha
Classifier: License :: OSI Approved :: MIT License
Classifier: Operating System :: OS Independent
Classifier: Programming Language :: Python :: 3
Classifier: Programming Language :: Python :: 3.10
Classifier: Programming Language :: Python :: 3.11
Classifier: Programming Language :: Python :: 3.12
Classifier: Typing :: Typed
Requires-Python: >=3.10
Requires-Dist: typer[all]
Provides-Extra: all
Requires-Dist: requirements-compare[quality]; extra == 'all'
Requires-Dist: requirements-compare[test]; extra == 'all'
Provides-Extra: quality
Requires-Dist: black; extra == 'quality'
Requires-Dist: flake8; extra == 'quality'
Requires-Dist: isort; extra == 'quality'
Requires-Dist: mypy; extra == 'quality'
Requires-Dist: pre-commit; extra == 'quality'
Requires-Dist: ruff; extra == 'quality'
Provides-Extra: test
Requires-Dist: coverage; extra == 'test'
Requires-Dist: pytest; extra == 'test'
